README.md
setup.py
pydevrant/__init__.py
pydevrant/basic.py
pydevrant.egg-info/PKG-INFO
pydevrant.egg-info/SOURCES.txt
pydevrant.egg-info/dependency_links.txt
pydevrant.egg-info/not-zip-safe
pydevrant.egg-info/requires.txt
pydevrant.egg-info/top_level.txt