Metadata-Version: 1.0
Name: pydevrant
Version: 0.21
Summary: Unofficial Python wrapper for the public devRant API
Home-page: https://github.com/SergioLaRosa/pydevrant
Author: Sergio La Rosa
Author-email: sergio.larosa89@gmail.com
License: MIT
Platform: UNKNOWN
